event_scale_http_client/__init__.py
event_scale_http_client/http.py
event_scale_http_client/response.py
event_scale_http_client-0.1.0.dist-info/METADATA
event_scale_http_client-0.1.0.dist-info/WHEEL
event_scale_http_client-0.1.0.dist-info/RECORD
