Metadata-Version: 2.4
Name: event_scale_http_client
Version: 0.1.0
Summary: A lightweight HTTP client with retry and form/JSON support
Author: Bedram Tamang
Author-email: tmgbedu@gmail.com
Requires-Python: >=3.12
Classifier: Programming Language :: Python :: 3
Classifier: License :: OSI Approved :: MIT License
Classifier: Operating System :: OS Independent
Requires-Dist: pytest (>=8.4.2,<9.0.0)
Requires-Dist: requests (>=2.32.5,<3.0.0)
Requires-Dist: responses (>=0.25.8,<0.26.0)
